mkdocs_gitlab/__init__.py
mkdocs_gitlab/markdown.py
mkdocs_gitlab/plugin.py
mkdocs_gitlab/py.typed
mkdocs_gitlab-1.4.0.dist-info/LICENSE
mkdocs_gitlab-1.4.0.dist-info/METADATA
mkdocs_gitlab-1.4.0.dist-info/WHEEL
mkdocs_gitlab-1.4.0.dist-info/entry_points.txt
mkdocs_gitlab-1.4.0.dist-info/RECORD
