Metadata-Version: 2.1
Name: mkdocs-gitlab
Version: 1.4.0
Summary: Use Gitlab CI variables for your docs
Home-page: https://pypi.org/project/mkdocs-gitlab
License: MIT
Author: Danil Akhtarov
Author-email: daxartio@gmail.com
Requires-Python: >=3.8,<4.0
Classifier: License :: OSI Approved :: MIT License
Classifier: Programming Language :: Python :: 3
Classifier: Programming Language :: Python :: 3.8
Classifier: Programming Language :: Python :: 3.9
Classifier: Programming Language :: Python :: 3.10
Classifier: Programming Language :: Python :: 3.11
Classifier: Programming Language :: Python :: 3.12
Requires-Dist: mkdocs
Project-URL: Repository, https://github.com/daxartio/mkdocs-gitlab
